winrt/__init__.py
winrt/_winrt.pyd
winrt/windows/ai/machinelearning/__init__.py
winrt/windows/ai/machinelearning/preview/__init__.py
winrt/windows/applicationmodel/__init__.py
winrt/windows/applicationmodel/activation/__init__.py
winrt/windows/applicationmodel/appextensions/__init__.py
winrt/windows/applicationmodel/appointments/__init__.py
winrt/windows/applicationmodel/appointments/appointmentsprovider/__init__.py
winrt/windows/applicationmodel/appointments/dataprovider/__init__.py
winrt/windows/applicationmodel/appservice/__init__.py
winrt/windows/applicationmodel/background/__init__.py
winrt/windows/applicationmodel/calls/__init__.py
winrt/windows/applicationmodel/calls/background/__init__.py
winrt/windows/applicationmodel/calls/provider/__init__.py
winrt/windows/applicationmodel/chat/__init__.py
winrt/windows/applicationmodel/communicationblocking/__init__.py
winrt/windows/applicationmodel/contacts/__init__.py
winrt/windows/applicationmodel/contacts/dataprovider/__init__.py
winrt/windows/applicationmodel/contacts/provider/__init__.py
winrt/windows/applicationmodel/core/__init__.py
winrt/windows/applicationmodel/datatransfer/__init__.py
winrt/windows/applicationmodel/datatransfer/dragdrop/__init__.py
winrt/windows/applicationmodel/datatransfer/dragdrop/core/__init__.py
winrt/windows/applicationmodel/datatransfer/sharetarget/__init__.py
winrt/windows/applicationmodel/email/__init__.py
winrt/windows/applicationmodel/email/dataprovider/__init__.py
winrt/windows/applicationmodel/extendedexecution/__init__.py
winrt/windows/applicationmodel/extendedexecution/foreground/__init__.py
winrt/windows/applicationmodel/lockscreen/__init__.py
winrt/windows/applicationmodel/payments/__init__.py
winrt/windows/applicationmodel/payments/provider/__init__.py
winrt/windows/applicationmodel/preview/holographic/__init__.py
winrt/windows/applicationmodel/resources/__init__.py
winrt/windows/applicationmodel/resources/core/__init__.py
winrt/windows/applicationmodel/search/__init__.py
winrt-1.0.20330.1.dist-info/LICENSE
winrt-1.0.20330.1.dist-info/METADATA
winrt-1.0.20330.1.dist-info/WHEEL
winrt-1.0.20330.1.dist-info/top_level.txt
winrt-1.0.20330.1.dist-info/RECORD
