Metadata-Version: 2.1
Name: winrt
Version: 1.0.20330.1
Summary: Access Windows Runtime APIs from Python
Home-page: https://github.com/Microsoft/xlang/tree/master/src/package/pywinrt/projection
Author: Microsoft Corporation
License: MIT
Platform: UNKNOWN
Classifier: Development Status :: 4 - Beta
Classifier: Environment :: Win32 (MS Windows)
Classifier: License :: OSI Approved :: MIT License
Classifier: Operating System :: Microsoft :: Windows :: Windows 10
Classifier: Programming Language :: Python :: 3.7
Classifier: Programming Language :: Python :: 3.8
Classifier: Programming Language :: Python :: 3.9
Classifier: Programming Language :: Python :: Implementation :: CPython
Classifier: Topic :: System :: Operating System
